gyvertwink/__init__.py
gyvertwink/gyver_twink.py
GyverTwinkApi-1.0.1.dist-info/LICENSE
GyverTwinkApi-1.0.1.dist-info/METADATA
GyverTwinkApi-1.0.1.dist-info/WHEEL
GyverTwinkApi-1.0.1.dist-info/top_level.txt
GyverTwinkApi-1.0.1.dist-info/RECORD
