Metadata-Version: 2.1
Name: GyverTwinkApi
Version: 1.0.1
Summary: Модуль для управления гирляндой GyverTwink через WiFi
Home-page: https://github.com/DeveloperDmitryKolyadin/GyverTwinkApi
Author: DevDK
Author-email: Dmitry@kolyadin.ru
Project-URL: Github, https://github.com/DeveloperDmitryKolyadin/GyverTwinkApi
Classifier: Programming Language :: Python :: 3
License-File: LICENSE
